[
  {
    "Id": "192caf10-1914-4846-81d6-fe2ed075dcac",
    "UserName": "asd",
    "Email": "asd",
    "Password": "asd",
    "UserRoles": [
      {
        "Id": "f331c61c-cc1d-4631-9651-d492f1e50f13",
        "Name": "Admin"
      }
    ]
  },
  {
    "Id": "192caf10-1914-4846-81d6-fe2ed075dcac",
    "UserName": "asd",
    "Email": "asd",
    "Password": "asd",
    "UserRoles": [
      {
        "Id": "f331c61c-cc1d-4631-9651-d492f1e50f13",
        "Name": "Admin"
      }
    ]
  },
  {
    "Id": "192caf10-1914-4846-81d6-fe2ed075dcac",
    "UserName": "asd",
    "Email": "asd",
    "Password": "asd",
    "UserRoles": [
      {
        "Id": "f331c61c-cc1d-4631-9651-d492f1e50f13",
        "Name": "Admin"
      }
    ]
  }
]